scripts/__init__.py
scripts/yo.py
src/__init__.py
src/data.py
src/messages.py
yo_cli-0.0.1.dist-info/DESCRIPTION.rst
yo_cli-0.0.1.dist-info/METADATA
yo_cli-0.0.1.dist-info/RECORD
yo_cli-0.0.1.dist-info/WHEEL
yo_cli-0.0.1.dist-info/entry_points.txt
yo_cli-0.0.1.dist-info/metadata.json
yo_cli-0.0.1.dist-info/top_level.txt
