Metadata-Version: 2.0
Name: yo-cli
Version: 0.0.1
Summary: Yo App Command Line Tool
Home-page: https://github.com/jaebradley/yo-cli
Author: Jae Bradley
Author-email: jae.b.bradley@gmail.com
License: UNKNOWN
Keywords: yo
Platform: UNKNOWN
Requires-Dist: Click (==6.7)
Requires-Dist: YoClient (==0.0.2)
Requires-Dist: termcolor (==1.1.0)
Requires-Dist: emoji (==0.4.5)
